tiko/__about__.py
tiko/__init__.py
tiko/install.py
tiko/logging.py
tiko/module.py
tiko/module_processing.py
tiko/terminal.py
tiko/modules/__init__.py
tiko/modules/bottom_module.py
tiko/modules/dua_module.py
tiko/modules/nu_module.py
tiko/modules/rust_module.py
tiko/modules/zellij_module.py
tiko-0.1.12.dist-info/METADATA
tiko-0.1.12.dist-info/WHEEL
tiko-0.1.12.dist-info/licenses/LICENSE.txt
tiko-0.1.12.dist-info/RECORD
